pytorch_check/__init__.py
pytorch_check/__main__.py
pytorch_check-1.0.3.dist-info/LICENSE
pytorch_check-1.0.3.dist-info/METADATA
pytorch_check-1.0.3.dist-info/WHEEL
pytorch_check-1.0.3.dist-info/entry_points.txt
pytorch_check-1.0.3.dist-info/top_level.txt
pytorch_check-1.0.3.dist-info/RECORD
