Metadata-Version: 2.1
Name: pytorch-check
Version: 1.0.3
Summary: Check PyTorch models for unsafe code
Home-page: https://github.com/clevcode/pytorch-check
Author: Joel Eriksson
Author-email: je@clevcode.org
Classifier: Development Status :: 5 - Production/Stable
Classifier: Intended Audience :: Developers
Classifier: License :: OSI Approved :: MIT License
Classifier: Programming Language :: Python :: 3
Classifier: Programming Language :: Python :: 3 :: Only
Requires-Python: >=3.7
License-File: LICENSE
Requires-Dist: fickling
Requires-Dist: colorama
